LICENSE
MANIFEST.in
README.md
setup.cfg
setup.py
LCSDIVE/AnalysisPhase1.py
LCSDIVE/AnalysisPhase1Job.py
LCSDIVE/AnalysisPhase1_pretrained.py
LCSDIVE/AnalysisPhase1_pretrainedJob.py
LCSDIVE/AnalysisPhase2.py
LCSDIVE/AnalysisPhase2ATJob.py
LCSDIVE/AnalysisPhase2NetworkJob.py
LCSDIVE/AnalysisPhase2RuleJob.py
LCSDIVE/DatasetSplitter.py
LCSDIVE/HClust.py
LCSDIVE/NetworkVisualization.py
LCSDIVE/Utilities.py
LCSDIVE/__init__.py
LCS_DIVE.egg-info/PKG-INFO
LCS_DIVE.egg-info/SOURCES.txt
LCS_DIVE.egg-info/dependency_links.txt
LCS_DIVE.egg-info/requires.txt
LCS_DIVE.egg-info/top_level.txt